pymigration
