Metadata-Version: 1.0
Name: pymigration
Version: 0.0.7
Summary: A generic tool for migrate in python.
Home-page: https://github.com/globocom/pymigration
Author: Team Search of globo.com
Author-email: busca@corp.globo.com
License: MIT
Keywords: migration
Platform: UNKNOWN
